[{"Line":13,"Code":"CS0029","Message":"Не удается неявно преобразовать тип \"string[]\" в \"System.Collections.Generic.IEnumerable<int>\". [CodeHelper.Service]","Source":"csharp"},{"Line":16,"Code":"CS1061","Message":"\"int\" не содержит определения \"Any\", и не удалось найти доступный метод расширения \"Any\", принимающий тип \"int\" в качестве первого аргумента (возможно, пропущена директива using или ссылка на сборку). [CodeHelper.Service]","Source":"csharp"},{"Line":4,"Code":"CS8019","Message":"Ненужная директива using. [CodeHelper.Service]","Source":"csharp"},{"Line":3,"Code":"CS8019","Message":"Ненужная директива using. [CodeHelper.Service]","Source":"csharp"},{"Line":2,"Code":"CS8019","Message":"Ненужная директива using. [CodeHelper.Service]","Source":"csharp"},{"Line":1,"Code":"CS8019","Message":"Ненужная директива using. [CodeHelper.Service]","Source":"csharp"},{"Line":5,"Code":"CS8019","Message":"Ненужная директива using. [CodeHelper.Service]","Source":"csharp"}]